objectdetection/__init__.py
objectdetection/eval_util.py
objectdetection/eval_util_test.py
objectdetection/export_inference_graph.py
objectdetection/export_tflite_ssd_graph.py
objectdetection/export_tflite_ssd_graph_lib.py
objectdetection/export_tflite_ssd_graph_lib_test.py
objectdetection/exporter.py
objectdetection/exporter_test.py
objectdetection/inputs.py
objectdetection/inputs_test.py
objectdetection/model_hparams.py
objectdetection/model_lib.py
objectdetection/model_lib_test.py
objectdetection/model_main.py
objectdetection/model_tpu_main.py
objectdetection/anchor_generators/__init__.py
objectdetection/anchor_generators/grid_anchor_generator.py
objectdetection/anchor_generators/grid_anchor_generator_test.py
objectdetection/anchor_generators/multiple_grid_anchor_generator.py
objectdetection/anchor_generators/multiple_grid_anchor_generator_test.py
objectdetection/anchor_generators/multiscale_grid_anchor_generator.py
objectdetection/anchor_generators/multiscale_grid_anchor_generator_test.py
objectdetection/box_coders/__init__.py
objectdetection/box_coders/faster_rcnn_box_coder.py
objectdetection/box_coders/faster_rcnn_box_coder_test.py
objectdetection/box_coders/keypoint_box_coder.py
objectdetection/box_coders/keypoint_box_coder_test.py
objectdetection/box_coders/mean_stddev_box_coder.py
objectdetection/box_coders/mean_stddev_box_coder_test.py
objectdetection/box_coders/square_box_coder.py
objectdetection/box_coders/square_box_coder_test.py
objectdetection/builders/__init__.py
objectdetection/builders/anchor_generator_builder.py
objectdetection/builders/anchor_generator_builder_test.py
objectdetection/builders/box_coder_builder.py
objectdetection/builders/box_coder_builder_test.py
objectdetection/builders/box_predictor_builder.py
objectdetection/builders/box_predictor_builder_test.py
objectdetection/builders/dataset_builder.py
objectdetection/builders/dataset_builder_test.py
objectdetection/builders/graph_rewriter_builder.py
objectdetection-0.0.2.dist-info/LICENSE
objectdetection-0.0.2.dist-info/METADATA
objectdetection-0.0.2.dist-info/WHEEL
objectdetection-0.0.2.dist-info/top_level.txt
objectdetection-0.0.2.dist-info/RECORD
