Metadata-Version: 2.1
Name: objectdetection
Version: 0.0.2
Summary: A package build from Tensorflow's object detection API.
Home-page: https://github.com/brandonschabell/models/tree/master/research/object_detection
Author: Brandon Schabell
Author-email: brandonschabell@gmail.com
License: Apache License 2.0
Platform: UNKNOWN
Classifier: Development Status :: 4 - Beta
Classifier: Intended Audience :: Developers
Classifier: Intended Audience :: Science/Research
Classifier: Programming Language :: Python :: 3.5
Classifier: Programming Language :: Python :: 3.6
Classifier: Topic :: Scientific/Engineering :: Artificial Intelligence
Requires-Python: >=3.5, !=3.7.*
Requires-Dist: tensorflow
Requires-Dist: Cython
Requires-Dist: contextlib2
Requires-Dist: pillow
Requires-Dist: lxml
Requires-Dist: jupyter
Requires-Dist: matplotlib
